nkt_basik/__init__.py
nkt_basik/bits_handling.py
nkt_basik/constants_and_enums.py
nkt_basik/dll/__init__.py
nkt_basik/dll/NKTP_DLL.py
nkt_basik/dll/NKTPDLL.dll
nkt_basik/dll/register_enums.py
nkt_basik/functions.py
nkt_basik/module.py
nkt_basik/utils.py
nkt_basik-0.3.3.dist-info/METADATA
nkt_basik-0.3.3.dist-info/WHEEL
nkt_basik-0.3.3.dist-info/RECORD
