Metadata-Version: 2.1
Name: nkt-basik
Version: 0.3.3
Summary: Python interface for the NKT Photonics Basik fiber seed laser
Home-page: https://github.com/ograsdijk/NKT-Basik
License: MIT
Author: ograsdijk
Author-email: o.grasdijk@gmail.com
Requires-Python: >=3.7,<4.0
Classifier: License :: OSI Approved :: MIT License
Classifier: Programming Language :: Python :: 3
Classifier: Programming Language :: Python :: 3.7
Classifier: Programming Language :: Python :: 3.8
Classifier: Programming Language :: Python :: 3.9
Classifier: Programming Language :: Python :: 3.10
Classifier: Programming Language :: Python :: 3.11
Project-URL: Repository, https://github.com/ograsdijk/NKT-Basik
